{
  "title":"What are the ideal conditions inside an office?",
  "options":[
    {
      "id": 1,
      "answers":[
        {
          "id": 1,
          "active": 0,
          "title": "Good pay",
          "correct": 1
        },
        {
          "id": 2,
          "active": 1,
          "title": "Bad pay",
          "correct": 0
        }
      ]
    },
    {
      "id": 2,
      "answers":[
        {
          "id": 3,
          "active": 1,
          "title": "A lot of meetings",
          "correct": 0
        },
        {
          "id": 4,
          "active": 0,
          "title": "Less meetings",
          "correct": 1
        }
      ]
    },
    {
      "id": 3,
      "answers":[
        {
          "id": 5,
          "active": 0,
          "title": "Free Coffee",
          "correct": 1
        },
        {
          "id": 6,
          "active": 1,
          "title": "Expensive Coffee",
          "correct": 0
        }
      ]
    },
    {
      "id": 4,
      "answers":[
        {
          "id": 7,
          "active": 0,
          "title": "Bear in office",
          "correct": 1
        },
        {
          "id": 8,
          "active": 1,
          "title": "Dog in office",
          "correct": 0
        }
      ]
    }
  ]
}